yolo_tiler/__init__.py
yolo_tiler/cli.py
yolo_tiler/yolo_tiler.py
yolo_tiling-0.0.27.dist-info/licenses/LICENSE
yolo_tiling-0.0.27.dist-info/METADATA
yolo_tiling-0.0.27.dist-info/WHEEL
yolo_tiling-0.0.27.dist-info/entry_points.txt
yolo_tiling-0.0.27.dist-info/top_level.txt
yolo_tiling-0.0.27.dist-info/RECORD
