Metadata-Version: 2.4
Name: yolo-tiling
Version: 0.0.27
Summary: Tile (slice) YOLO Dataset for Small Objects Detection and Instance Segmentation
Author-email: Jordan Pierce <jordan.pierce@noaa.gov>
License: MIT License
Project-URL: Homepage, https://github.com/Jordan-Pierce/yolo-tiling
Keywords: yolo-tiling
Classifier: Intended Audience :: Developers
Classifier: License :: OSI Approved :: MIT License
Classifier: Natural Language :: English
Classifier: Programming Language :: Python :: 3.9
Classifier: Programming Language :: Python :: 3.10
Classifier: Programming Language :: Python :: 3.11
Classifier: Programming Language :: Python :: 3.12
Requires-Python: >=3.9
License-File: LICENSE
Requires-Dist: numpy
Requires-Dist: tqdm
Requires-Dist: pandas
Requires-Dist: Shapely
Requires-Dist: rasterio
Requires-Dist: opencv-python
Requires-Dist: matplotlib
Requires-Dist: PyYAML
Dynamic: license-file
